learning_logs/__init__.py
learning_logs/admin.py
learning_logs/apps.py
learning_logs/forms.py
learning_logs/models.py
learning_logs/tests.py
learning_logs/urls.py
learning_logs/views.py
learning_logs/migrations/0001_initial.py
learning_logs/migrations/0002_entry.py
learning_logs/migrations/0003_rename_date_added_entry_date_added.py
learning_logs/migrations/0004_topic_owner.py
learning_logs/migrations/__init__.py
learning_logs/templates/.DS_Store
learning_logs/templates/learning_logs/.DS_Store
learning_logs/templates/learning_logs/base.html
learning_logs/templates/learning_logs/edit_entry.html
learning_logs/templates/learning_logs/index.html
learning_logs/templates/learning_logs/new_entry.html
learning_logs/templates/learning_logs/new_topic.html
learning_logs/templates/learning_logs/topic.html
learning_logs/templates/learning_logs/topics.html
users/__init__.py
users/admin.py
users/apps.py
users/models.py
users/tests.py
users/urls.py
users/views.py
users/migrations/__init__.py
users/templates/.DS_Store
users/templates/registration/logged_out.html
users/templates/registration/login.html
users/templates/registration/register.html
django_learning_log-1.1.dist-info/LICENSE
django_learning_log-1.1.dist-info/METADATA
django_learning_log-1.1.dist-info/WHEEL
django_learning_log-1.1.dist-info/top_level.txt
django_learning_log-1.1.dist-info/RECORD
